jem/__init__.py
jem/cli.py
jem/features.py
jem/filters.py
jem/logging.py
jem/signal_stats.py
jem/simulation.py
jem/utils.py
jem/tests/__init__.py
jem/tests/conftest.py
jem/tests/test_examples.py
jem-0.3.12.dist-info/AUTHORS.rst
jem-0.3.12.dist-info/LICENSE
jem-0.3.12.dist-info/METADATA
jem-0.3.12.dist-info/WHEEL
jem-0.3.12.dist-info/entry_points.txt
jem-0.3.12.dist-info/top_level.txt
jem-0.3.12.dist-info/RECORD
