Metadata-Version: 2.1
Name: jem
Version: 0.3.12
Summary: Python package for MRI and electrophysiology analysis.
Home-page: https://github.com/inatilab/jem
Author: Inati Lab, NINDS, NIH
Author-email: souheil.inati@gmail.com
License: Public Domain
Platform: UNKNOWN
Classifier: Development Status :: 2 - Pre-Alpha
Classifier: Natural Language :: English
Classifier: Programming Language :: Python :: 3
License-File: LICENSE
License-File: AUTHORS.rst
Requires-Dist: click
Requires-Dist: nibabel
Requires-Dist: numpy
Requires-Dist: scipy
